LinuxRumenjiaochengCYuyanBianchengWang/README.md
LinuxRumenjiaochengCYuyanBianchengWang/__init__.py
LinuxRumenjiaochengCYuyanBianchengWang/__main__.py
LinuxRumenjiaochengCYuyanBianchengWang/file.epub
LinuxRumenjiaochengCYuyanBianchengWang/index.html
LinuxRumenjiaochengCYuyanBianchengWang/css/__init__.py
LinuxRumenjiaochengCYuyanBianchengWang/css/annotations.css
LinuxRumenjiaochengCYuyanBianchengWang/css/main.css
LinuxRumenjiaochengCYuyanBianchengWang/css/normalize.css
LinuxRumenjiaochengCYuyanBianchengWang/css/popup.css
LinuxRumenjiaochengCYuyanBianchengWang/font/__init__.py
LinuxRumenjiaochengCYuyanBianchengWang/font/fontello.eot
LinuxRumenjiaochengCYuyanBianchengWang/font/fontello.svg
LinuxRumenjiaochengCYuyanBianchengWang/font/fontello.ttf
LinuxRumenjiaochengCYuyanBianchengWang/font/fontello.woff
LinuxRumenjiaochengCYuyanBianchengWang/img/__init__.py
LinuxRumenjiaochengCYuyanBianchengWang/img/annotator-glyph-sprite.png
LinuxRumenjiaochengCYuyanBianchengWang/img/annotator-icon-sprite.png
LinuxRumenjiaochengCYuyanBianchengWang/img/apple-touch-icon.png
LinuxRumenjiaochengCYuyanBianchengWang/img/cancelfullscreen.png
LinuxRumenjiaochengCYuyanBianchengWang/img/close.png
LinuxRumenjiaochengCYuyanBianchengWang/img/fullscreen.png
LinuxRumenjiaochengCYuyanBianchengWang/img/loader.gif
LinuxRumenjiaochengCYuyanBianchengWang/img/menu-icon.png
LinuxRumenjiaochengCYuyanBianchengWang/img/save.png
LinuxRumenjiaochengCYuyanBianchengWang/img/saved.png
LinuxRumenjiaochengCYuyanBianchengWang/img/settings-s.png
LinuxRumenjiaochengCYuyanBianchengWang/img/settings.png
LinuxRumenjiaochengCYuyanBianchengWang/img/star.png
LinuxRumenjiaochengCYuyanBianchengWang/js/__init__.py
LinuxRumenjiaochengCYuyanBianchengWang/js/epub.js
LinuxRumenjiaochengCYuyanBianchengWang/js/epub.min.js
LinuxRumenjiaochengCYuyanBianchengWang/js/epub.min.map
LinuxRumenjiaochengCYuyanBianchengWang/js/hooks.min.js
LinuxRumenjiaochengCYuyanBianchengWang/js/hooks.min.map
linux_rumenjiaocheng_c_yuyan_biancheng_wang-2024.3.2.0.dist-info/METADATA
linux_rumenjiaocheng_c_yuyan_biancheng_wang-2024.3.2.0.dist-info/WHEEL
linux_rumenjiaocheng_c_yuyan_biancheng_wang-2024.3.2.0.dist-info/entry_points.txt
linux_rumenjiaocheng_c_yuyan_biancheng_wang-2024.3.2.0.dist-info/top_level.txt
linux_rumenjiaocheng_c_yuyan_biancheng_wang-2024.3.2.0.dist-info/RECORD
